hepatitis_c_predictor-1.0.0.dist-info/licenses/LICENSE
src/__init__.py
src/app.py
src/data.py
src/models.py
src/train.py
src/visualization.py
src/visualization_demo.py
hepatitis_c_predictor-1.0.0.dist-info/METADATA
hepatitis_c_predictor-1.0.0.dist-info/WHEEL
hepatitis_c_predictor-1.0.0.dist-info/entry_points.txt
hepatitis_c_predictor-1.0.0.dist-info/top_level.txt
hepatitis_c_predictor-1.0.0.dist-info/RECORD
