Metadata-Version: 2.4
Name: hepatitis-c-predictor
Version: 1.0.0
Summary: Interactive ML application for Hepatitis C classification using PyTorch with Streamlit interface
Author: Endika, Igor, Wassim
License-Expression: MIT
Project-URL: Homepage, https://github.com/Ninjalice/HEPATITIS_C_MODEL
Project-URL: Documentation, https://ninjalice.github.io/HEPATITIS_C_MODEL/src.html
Project-URL: Repository, https://github.com/Ninjalice/HEPATITIS_C_MODEL
Project-URL: Issues, https://github.com/Ninjalice/HEPATITIS_C_MODEL/issues
Keywords: machine-learning,pytorch,hepatitis-c,classification,streamlit,medical-ai,deep-learning,neural-network
Classifier: Development Status :: 4 - Beta
Classifier: Intended Audience :: Science/Research
Classifier: Intended Audience :: Healthcare Industry
Classifier: Intended Audience :: Education
Classifier: Topic :: Scientific/Engineering :: Artificial Intelligence
Classifier: Topic :: Scientific/Engineering :: Medical Science Apps.
Classifier: Programming Language :: Python :: 3
Classifier: Programming Language :: Python :: 3.10
Classifier: Programming Language :: Python :: 3.11
Classifier: Programming Language :: Python :: 3.12
Classifier: Operating System :: OS Independent
Requires-Python: >=3.10
License-File: LICENSE
Requires-Dist: streamlit~=1.50.0
Requires-Dist: pandas~=2.3.0
Requires-Dist: numpy~=2.2.0
Requires-Dist: matplotlib~=3.10.0
Requires-Dist: seaborn~=0.13.0
Requires-Dist: plotly~=6.3.1
Requires-Dist: torch~=2.8.0
Requires-Dist: scikit-learn~=1.7.0
Provides-Extra: dev
Requires-Dist: pytest>=7.0.0; extra == "dev"
Requires-Dist: black>=23.0.0; extra == "dev"
Requires-Dist: flake8>=6.0.0; extra == "dev"
Provides-Extra: notebooks
Requires-Dist: jupyter>=1.0.0; extra == "notebooks"
Requires-Dist: ipykernel>=6.22.0; extra == "notebooks"
Requires-Dist: ipython>=8.0.0; extra == "notebooks"
Provides-Extra: docs
Requires-Dist: pdoc>=14.0.0; extra == "docs"
Dynamic: license-file
